magic_filter/__init__.py
magic_filter/attrdict.py
magic_filter/exceptions.py
magic_filter/helper.py
magic_filter/magic.py
magic_filter/operations/__init__.py
magic_filter/operations/base.py
magic_filter/operations/call.py
magic_filter/operations/cast.py
magic_filter/operations/combination.py
magic_filter/operations/comparator.py
magic_filter/operations/function.py
magic_filter/operations/getattr.py
magic_filter/operations/getitem.py
magic_filter/operations/selector.py
magic_filter/py.typed
magic_filter/util.py
magic_filter-1.0.8.dist-info/WHEEL
magic_filter-1.0.8.dist-info/METADATA
magic_filter-1.0.8.dist-info/RECORD
